[
    {
        "ProductId": "43f51afb-b935-48fb-893e-90dc3088a73f",
        "Status": "Using",
        "Url": "http://placekitten.com/g/300/300"
    },
    {
        "ProductId": "43f51afb-b935-48fb-893e-90dc3088a73f",
        "Status": "Using",
        "Url": "http://placekitten.com/g/300/300"
    },
    {
        "ProductId": "43f51afb-b935-48fb-893e-90dc3088a73f",
        "Status": "Using",
        "Url": "http://placekitten.com/g/300/300"
    },
    {
        "ProductId": "6e33b0fb-300b-470a-a6f2-978a580bdddf",
        "Status": "Using",
        "Url": "http://placekitten.com/g/300/300"
    },
    {
        "ProductId": "6e33b0fb-300b-470a-a6f2-978a580bdddf",
        "Status": "Remove",
        "Url": "http://placekitten.com/g/300/300"
    },
    {
        "ProductId": "6e33b0fb-300b-470a-a6f2-978a580bdddf",
        "Status": "Using",
        "Url": "http://placekitten.com/g/300/300"
    },
    {
        "ProductId": "3b29be19-ce96-46ce-8dc5-c6bf34a02530",
        "Status": "Using",
        "Url": "http://placekitten.com/g/300/300"
    },
    {
        "ProductId": "3b29be19-ce96-46ce-8dc5-c6bf34a02530",
        "Status": "Using",
        "Url": "http://placekitten.com/g/300/300"
    },
    {
        "ProductId": "3b29be19-ce96-46ce-8dc5-c6bf34a02530",
        "Status": "Using",
        "Url": "http://placekitten.com/g/300/300"
    },
    {
        "ProductId": "3b29be19-ce96-46ce-8dc5-c6bf34a02530",
        "Status": "Using",
        "Url": "http://placekitten.com/g/300/300"
    },
    {
        "ProductId": "8da96b9e-91fa-4f84-bef0-e162eded6b29",
        "Status": "Using",
        "Url": "http://placekitten.com/g/300/300"
    },
    {
        "ProductId": "8da96b9e-91fa-4f84-bef0-e162eded6b29",
        "Status": "Using",
        "Url": "http://placekitten.com/g/300/300"
    },
    {
        "ProductId": "118cda2b-cb82-4749-bd07-3d4bee175bb6",
        "Status": "Using",
        "Url": "http://placekitten.com/g/300/300"
    },
    {
        "ProductId": "118cda2b-cb82-4749-bd07-3d4bee175bb6",
        "Status": "Using",
        "Url": "http://placekitten.com/g/300/300"
    },
    {
        "ProductId": "2d8fbdae-3835-4d03-8d20-924c1f6f6910",
        "Status": "Using",
        "Url": "http://placekitten.com/g/300/300"
    },
    {
        "ProductId": "2d8fbdae-3835-4d03-8d20-924c1f6f6910",
        "Status": "Using",
        "Url": "http://placekitten.com/g/300/300"
    },
    {
        "ProductId": "2d8fbdae-3835-4d03-8d20-924c1f6f6910",
        "Status": "Using",
        "Url": "http://placekitten.com/g/300/300"
    },
    {
        "ProductId": "2d8fbdae-3835-4d03-8d20-924c1f6f6910",
        "Status": "Using",
        "Url": "http://placekitten.com/g/300/300"
    },
    {
        "ProductId": "9de69a44-fee2-4c0a-b3c9-4d05e14ded8f",
        "Status": "Using",
        "Url": "http://placekitten.com/g/300/300"
    },
    {
        "ProductId": "9de69a44-fee2-4c0a-b3c9-4d05e14ded8f",
        "Status": "Using",
        "Url": "http://placekitten.com/g/300/300"
    },
    {
        "ProductId": "9de69a44-fee2-4c0a-b3c9-4d05e14ded8f",
        "Status": "Using",
        "Url": "http://placekitten.com/g/300/300"
    },
    {
        "ProductId": "9de69a44-fee2-4c0a-b3c9-4d05e14ded8f",
        "Status": "Using",
        "Url": "http://placekitten.com/g/300/300"
    },
    {
        "ProductId": "9de69a44-fee2-4c0a-b3c9-4d05e14ded8f",
        "Status": "Using",
        "Url": "http://placekitten.com/g/300/300"
    },
    {
        "ProductId": "326ad98f-948c-4081-95c3-298dfe46a705",
        "Status": "Using",
        "Url": "http://placekitten.com/g/300/300"
    },
    {
        "ProductId": "326ad98f-948c-4081-95c3-298dfe46a705",
        "Status": "Using",
        "Url": "http://placekitten.com/g/300/300"
    },
    {
        "ProductId": "54d5e86b-f4fc-43a8-8fbf-a3d3733f6d85",
        "Status": "Using",
        "Url": "http://placekitten.com/g/300/300"
    },
    {
        "ProductId": "3eac1cc3-3166-4d1d-a8f0-59d32f0468be",
        "Status": "Using",
        "Url": "http://placekitten.com/g/300/300"
    },
    {
        "ProductId": "edbc6b1c-5e84-4127-bce3-67fb47bc11e4",
        "Status": "Using",
        "Url": "http://placekitten.com/g/300/300"
    },
    {
        "ProductId": "907deaf0-cba5-491e-ab42-a20bbaaa040b",
        "Status": "Using",
        "Url": "http://placekitten.com/g/300/300"
    },
    {
        "ProductId": "02d9d1f8-2761-429d-b47f-1d45f62b1802",
        "Status": "Using",
        "Url": "http://placekitten.com/g/300/300"
    },
    {
        "ProductId": "a2bf8a79-705e-47d4-a2bd-44049337d60b",
        "Status": "Remove",
        "Url": "http://placekitten.com/g/300/300"
    },
    {
        "ProductId": "e340e14b-d498-4115-8698-6f7b7a5b8a5f",
        "Status": "Using",
        "Url": "http://placekitten.com/g/300/300"
    },
    {
        "ProductId": "05420a89-ea89-40ca-bc5c-cd12f1afaf09",
        "Status": "Using",
        "Url": "http://placekitten.com/g/300/300"
    },
    {
        "ProductId": "ce72684b-569f-4427-a539-f71f4c134372",
        "Status": "Using",
        "Url": "http://placekitten.com/g/300/300"
    },
    {
        "ProductId": "2a6557e9-7727-4854-9ac6-44756849bd41",
        "Status": "Using",
        "Url": "http://placekitten.com/g/300/300"
    },
    {
        "ProductId": "a8238610-ba6a-44eb-a229-c1f90647bcf3",
        "Status": "Using",
        "Url": "http://placekitten.com/g/300/300"
    },
    {
        "ProductId": "f0cb29ba-76d0-4737-8565-5de26e4c24e4",
        "Status": "Using",
        "Url": "http://placekitten.com/g/300/300"
    },
    {
        "ProductId": "22c4b828-0c4d-42ae-9c9e-d339c1fa951d",
        "Status": "Using",
        "Url": "http://placekitten.com/g/300/300"
    },
    {
        "ProductId": "f54924cc-8c8a-4afc-869a-d67c89815e8c",
        "Status": "Using",
        "Url": "http://placekitten.com/g/300/300"
    },
    {
        "ProductId": "b285cf2b-55ea-4d7a-acf3-3f32ae27f195",
        "Status": "Using",
        "Url": "http://placekitten.com/g/300/300"
    },
    {
        "ProductId": "2513250e-261d-4efa-b874-83cd1267c8ce",
        "Status": "Using",
        "Url": "http://placekitten.com/g/300/300"
    },
    {
        "ProductId": "7854cc1b-64ab-4062-aa0f-ba02aeb36ce6",
        "Status": "Using",
        "Url": "http://placekitten.com/g/300/300"
    },
    {
        "ProductId": "945ce915-201f-4605-b4cd-8db15ca5836b",
        "Status": "Using",
        "Url": "http://placekitten.com/g/300/300"
    },
    {
        "ProductId": "4226947b-a632-45b1-9e3d-28b708fa91a9",
        "Status": "Using",
        "Url": "http://placekitten.com/g/300/300"
    },
    {
        "ProductId": "57f7fce4-1f00-4da9-bd57-2e1c30b1260a",
        "Status": "Using",
        "Url": "http://placekitten.com/g/300/300"
    },
    {
        "ProductId": "6d540f22-1587-4b73-bfd0-a467ae00ac22",
        "Status": "Using",
        "Url": "http://placekitten.com/g/300/300"
    },
    {
        "ProductId": "438838e4-ef46-4f60-af23-b8060c52ce78",
        "Status": "Using",
        "Url": "http://placekitten.com/g/300/300"
    },
    {
        "ProductId": "67a82b71-b359-48d2-84aa-fe4a6cd9be80",
        "Status": "Using",
        "Url": "http://placekitten.com/g/300/300"
    },
    {
        "ProductId": "d36210e7-e4c2-4826-b288-5a8f67ca5793",
        "Status": "Using",
        "Url": "http://placekitten.com/g/300/300"
    },
    {
        "ProductId": "88dfcf99-43e4-4823-b88b-0cff516a5c38",
        "Status": "Using",
        "Url": "http://placekitten.com/g/300/300"
    },
    {
        "ProductId": "4b898315-cb1a-42b1-8a16-71f7e7a422d7",
        "Status": "Using",
        "Url": "http://placekitten.com/g/300/300"
    },
    {
        "ProductId": "c3773ce0-19aa-4e5e-8bd1-b579ff85c426",
        "Status": "Using",
        "Url": "http://placekitten.com/g/300/300"
    },
    {
        "ProductId": "299e65a7-5827-49b1-b08d-df237a7b01a7",
        "Status": "Using",
        "Url": "http://placekitten.com/g/300/300"
    },
    {
        "ProductId": "6b62b0f7-45a8-4032-8aeb-402af3ae8406",
        "Status": "Using",
        "Url": "http://placekitten.com/g/300/300"
    },
    {
        "ProductId": "6050fe69-74d3-4f50-9fc4-a78c4fc72609",
        "Status": "Using",
        "Url": "http://placekitten.com/g/300/300"
    },
    {
        "ProductId": "b065f698-e3b6-42d0-8534-75f6d27618e7",
        "Status": "Using",
        "Url": "http://placekitten.com/g/300/300"
    },
    {
        "ProductId": "bce11432-c2a8-4ad2-a49c-2a44bfe6a16d",
        "Status": "Using",
        "Url": "http://placekitten.com/g/300/300"
    },
    {
        "ProductId": "5a27d0b2-e094-47ca-9a99-1b825439f107",
        "Status": "Using",
        "Url": "http://placekitten.com/g/300/300"
    },
    {
        "ProductId": "1f757f9c-b268-41bd-8749-f995cbb468ea",
        "Status": "Using",
        "Url": "http://placekitten.com/g/300/300"
    },
    {
        "ProductId": "94fd8580-d2dc-42ac-a29a-d7a855e74a80",
        "Status": "Using",
        "Url": "http://placekitten.com/g/300/300"
    },
    {
        "ProductId": "5f2ae358-c830-4d59-addf-db8db428d87f",
        "Status": "Using",
        "Url": "http://placekitten.com/g/300/300"
    },
    {
        "ProductId": "f9aabc94-e10a-4fbe-9cf3-92fc0f6e7a73",
        "Status": "Using",
        "Url": "http://placekitten.com/g/300/300"
    },
    {
        "ProductId": "65c5da59-0427-424c-a610-02793217e6a0",
        "Status": "Using",
        "Url": "http://placekitten.com/g/300/300"
    },
    {
        "ProductId": "35cc7908-ad9f-4211-8668-fb8a2954134d",
        "Status": "Using",
        "Url": "http://placekitten.com/g/300/300"
    },
    {
        "ProductId": "50175acc-dfbf-43ac-86aa-aee37f804f5c",
        "Status": "Using",
        "Url": "http://placekitten.com/g/300/300"
    },
    {
        "ProductId": "1808d7cf-405a-4302-9944-f1767f5ab9ff",
        "Status": "Using",
        "Url": "http://placekitten.com/g/300/300"
    },
    {
        "ProductId": "1808d7cf-405a-4302-9944-f1767f5ab9ff",
        "Status": "Using",
        "Url": "http://placekitten.com/g/300/300"
    },
    {
        "ProductId": "1808d7cf-405a-4302-9944-f1767f5ab9ff",
        "Status": "Using",
        "Url": "http://placekitten.com/g/300/300"
    },
    {
        "ProductId": "43f51afb-b935-48fb-893e-90dc3088a73f",
        "Status": "Using",
        "Url": "http://placekitten.com/g/300/300"
    },
    {
        "ProductId": "6e33b0fb-300b-470a-a6f2-978a580bdddf",
        "Status": "Using",
        "Url": "http://placekitten.com/g/300/300"
    },
    {
        "ProductId": "3b29be19-ce96-46ce-8dc5-c6bf34a02530",
        "Status": "Using",
        "Url": "http://placekitten.com/g/300/300"
    },
    {
        "ProductId": "8da96b9e-91fa-4f84-bef0-e162eded6b29",
        "Status": "Using",
        "Url": "http://placekitten.com/g/300/300"
    },
    {
        "ProductId": "118cda2b-cb82-4749-bd07-3d4bee175bb6",
        "Status": "Using",
        "Url": "http://placekitten.com/g/300/300"
    },
    {
        "ProductId": "2d8fbdae-3835-4d03-8d20-924c1f6f6910",
        "Status": "Using",
        "Url": "http://placekitten.com/g/300/300"
    },
    {
        "ProductId": "326ad98f-948c-4081-95c3-298dfe46a705",
        "Status": "Using",
        "Url": "http://placekitten.com/g/300/300"
    },
    {
        "ProductId": "54d5e86b-f4fc-43a8-8fbf-a3d3733f6d85",
        "Status": "Using",
        "Url": "http://placekitten.com/g/300/300"
    },
    {
        "ProductId": "3eac1cc3-3166-4d1d-a8f0-59d32f0468be",
        "Status": "Using",
        "Url": "http://placekitten.com/g/300/300"
    },
    {
        "ProductId": "edbc6b1c-5e84-4127-bce3-67fb47bc11e4",
        "Status": "Using",
        "Url": "http://placekitten.com/g/300/300"
    },
    {
        "ProductId": "907deaf0-cba5-491e-ab42-a20bbaaa040b",
        "Status": "Using",
        "Url": "http://placekitten.com/g/300/300"
    },
    {
        "ProductId": "02d9d1f8-2761-429d-b47f-1d45f62b1802",
        "Status": "Using",
        "Url": "http://placekitten.com/g/300/300"
    },
    {
        "ProductId": "a2bf8a79-705e-47d4-a2bd-44049337d60b",
        "Status": "Using",
        "Url": "http://placekitten.com/g/300/300"
    },
    {
        "ProductId": "e340e14b-d498-4115-8698-6f7b7a5b8a5f",
        "Status": "Using",
        "Url": "http://placekitten.com/g/300/300"
    },
    {
        "ProductId": "05420a89-ea89-40ca-bc5c-cd12f1afaf09",
        "Status": "Using",
        "Url": "http://placekitten.com/g/300/300"
    },
    {
        "ProductId": "ce72684b-569f-4427-a539-f71f4c134372",
        "Status": "Using",
        "Url": "http://placekitten.com/g/300/300"
    },
    {
        "ProductId": "2a6557e9-7727-4854-9ac6-44756849bd41",
        "Status": "Using",
        "Url": "http://placekitten.com/g/300/300"
    },
    {
        "ProductId": "a8238610-ba6a-44eb-a229-c1f90647bcf3",
        "Status": "Using",
        "Url": "http://placekitten.com/g/300/300"
    },
    {
        "ProductId": "f0cb29ba-76d0-4737-8565-5de26e4c24e4",
        "Status": "Using",
        "Url": "http://placekitten.com/g/300/300"
    },
    {
        "ProductId": "22c4b828-0c4d-42ae-9c9e-d339c1fa951d",
        "Status": "Using",
        "Url": "http://placekitten.com/g/300/300"
    },
    {
        "ProductId": "f54924cc-8c8a-4afc-869a-d67c89815e8c",
        "Status": "Using",
        "Url": "http://placekitten.com/g/300/300"
    },
    {
        "ProductId": "b285cf2b-55ea-4d7a-acf3-3f32ae27f195",
        "Status": "Using",
        "Url": "http://placekitten.com/g/300/300"
    },
    {
        "ProductId": "2513250e-261d-4efa-b874-83cd1267c8ce",
        "Status": "Using",
        "Url": "http://placekitten.com/g/300/300"
    },
    {
        "ProductId": "7854cc1b-64ab-4062-aa0f-ba02aeb36ce6",
        "Status": "Using",
        "Url": "http://placekitten.com/g/300/300"
    },
    {
        "ProductId": "57f7fce4-1f00-4da9-bd57-2e1c30b1260a",
        "Status": "Remove",
        "Url": "http://placekitten.com/g/300/300"
    },
    {
        "ProductId": "6d540f22-1587-4b73-bfd0-a467ae00ac22",
        "Status": "Using",
        "Url": "http://placekitten.com/g/300/300"
    },
    {
        "ProductId": "438838e4-ef46-4f60-af23-b8060c52ce78",
        "Status": "Using",
        "Url": "http://placekitten.com/g/300/300"
    },
    {
        "ProductId": "67a82b71-b359-48d2-84aa-fe4a6cd9be80",
        "Status": "Using",
        "Url": "http://placekitten.com/g/300/300"
    },
    {
        "ProductId": "d36210e7-e4c2-4826-b288-5a8f67ca5793",
        "Status": "Using",
        "Url": "http://placekitten.com/g/300/300"
    },
    {
        "ProductId": "88dfcf99-43e4-4823-b88b-0cff516a5c38",
        "Status": "Using",
        "Url": "http://placekitten.com/g/300/300"
    },
    {
        "ProductId": "4b898315-cb1a-42b1-8a16-71f7e7a422d7",
        "Status": "Using",
        "Url": "http://placekitten.com/g/300/300"
    },
    {
        "ProductId": "c3773ce0-19aa-4e5e-8bd1-b579ff85c426",
        "Status": "Using",
        "Url": "http://placekitten.com/g/300/300"
    },
    {
        "ProductId": "299e65a7-5827-49b1-b08d-df237a7b01a7",
        "Status": "Using",
        "Url": "http://placekitten.com/g/300/300"
    },
    {
        "ProductId": "6b62b0f7-45a8-4032-8aeb-402af3ae8406",
        "Status": "Using",
        "Url": "http://placekitten.com/g/300/300"
    },
    {
        "ProductId": "6050fe69-74d3-4f50-9fc4-a78c4fc72609",
        "Status": "Using",
        "Url": "http://placekitten.com/g/300/300"
    },
    {
        "ProductId": "57f7fce4-1f00-4da9-bd57-2e1c30b1260a",
        "Status": "Using",
        "Url": "http://placekitten.com/g/300/300"
    },
    {
        "ProductId": "6d540f22-1587-4b73-bfd0-a467ae00ac22",
        "Status": "Using",
        "Url": "http://placekitten.com/g/300/300"
    },
    {
        "ProductId": "438838e4-ef46-4f60-af23-b8060c52ce78",
        "Status": "Using",
        "Url": "http://placekitten.com/g/300/300"
    },
    {
        "ProductId": "67a82b71-b359-48d2-84aa-fe4a6cd9be80",
        "Status": "Using",
        "Url": "http://placekitten.com/g/300/300"
    },
    {
        "ProductId": "d36210e7-e4c2-4826-b288-5a8f67ca5793",
        "Status": "Using",
        "Url": "http://placekitten.com/g/300/300"
    },
    {
        "ProductId": "88dfcf99-43e4-4823-b88b-0cff516a5c38",
        "Status": "Using",
        "Url": "http://placekitten.com/g/300/300"
    },
    {
        "ProductId": "4b898315-cb1a-42b1-8a16-71f7e7a422d7",
        "Status": "Using",
        "Url": "http://placekitten.com/g/300/300"
    },
    {
        "ProductId": "c3773ce0-19aa-4e5e-8bd1-b579ff85c426",
        "Status": "Using",
        "Url": "http://placekitten.com/g/300/300"
    },
    {
        "ProductId": "299e65a7-5827-49b1-b08d-df237a7b01a7",
        "Status": "Using",
        "Url": "http://placekitten.com/g/300/300"
    },
    {
        "ProductId": "6b62b0f7-45a8-4032-8aeb-402af3ae8406",
        "Status": "Using",
        "Url": "http://placekitten.com/g/300/300"
    },
    {
        "ProductId": "6050fe69-74d3-4f50-9fc4-a78c4fc72609",
        "Status": "Using",
        "Url": "http://placekitten.com/g/300/300"
    },
    {
        "ProductId": "b065f698-e3b6-42d0-8534-75f6d27618e7",
        "Status": "Using",
        "Url": "http://placekitten.com/g/300/300"
    },
    {
        "ProductId": "bce11432-c2a8-4ad2-a49c-2a44bfe6a16d",
        "Status": "Using",
        "Url": "http://placekitten.com/g/300/300"
    },
    {
        "ProductId": "5a27d0b2-e094-47ca-9a99-1b825439f107",
        "Status": "Using",
        "Url": "http://placekitten.com/g/300/300"
    },
    {
        "ProductId": "1f757f9c-b268-41bd-8749-f995cbb468ea",
        "Status": "Using",
        "Url": "http://placekitten.com/g/300/300"
    },
    {
        "ProductId": "94fd8580-d2dc-42ac-a29a-d7a855e74a80",
        "Status": "Using",
        "Url": "http://placekitten.com/g/300/300"
    },
    {
        "ProductId": "5f2ae358-c830-4d59-addf-db8db428d87f",
        "Status": "Using",
        "Url": "http://placekitten.com/g/300/300"
    },
    {
        "ProductId": "f9aabc94-e10a-4fbe-9cf3-92fc0f6e7a73",
        "Status": "Using",
        "Url": "http://placekitten.com/g/300/300"
    },
    {
        "ProductId": "65c5da59-0427-424c-a610-02793217e6a0",
        "Status": "Using",
        "Url": "http://placekitten.com/g/300/300"
    },
    {
        "ProductId": "6050fe69-74d3-4f50-9fc4-a78c4fc72609",
        "Status": "Using",
        "Url": "http://placekitten.com/g/300/300"
    },
    {
        "ProductId": "b065f698-e3b6-42d0-8534-75f6d27618e7",
        "Status": "Using",
        "Url": "http://placekitten.com/g/300/300"
    },
    {
        "ProductId": "bce11432-c2a8-4ad2-a49c-2a44bfe6a16d",
        "Status": "Using",
        "Url": "http://placekitten.com/g/300/300"
    },
    {
        "ProductId": "5a27d0b2-e094-47ca-9a99-1b825439f107",
        "Status": "Using",
        "Url": "http://placekitten.com/g/300/300"
    },
    {
        "ProductId": "1f757f9c-b268-41bd-8749-f995cbb468ea",
        "Status": "Using",
        "Url": "http://placekitten.com/g/300/300"
    },
    {
        "ProductId": "94fd8580-d2dc-42ac-a29a-d7a855e74a80",
        "Status": "Remove",
        "Url": "http://placekitten.com/g/300/300"
    },
    {
        "ProductId": "5f2ae358-c830-4d59-addf-db8db428d87f",
        "Status": "Using",
        "Url": "http://placekitten.com/g/300/300"
    },
    {
        "ProductId": "94fd8580-d2dc-42ac-a29a-d7a855e74a80",
        "Status": "Using",
        "Url": "http://placekitten.com/g/300/300"
    },
    {
        "ProductId": "5f2ae358-c830-4d59-addf-db8db428d87f",
        "Status": "Using",
        "Url": "http://placekitten.com/g/300/300"
    },
    {
        "ProductId": "f9aabc94-e10a-4fbe-9cf3-92fc0f6e7a73",
        "Status": "Using",
        "Url": "http://placekitten.com/g/300/300"
    },
    {
        "ProductId": "65c5da59-0427-424c-a610-02793217e6a0",
        "Status": "Using",
        "Url": "http://placekitten.com/g/300/300"
    },
    {
        "ProductId": "35cc7908-ad9f-4211-8668-fb8a2954134d",
        "Status": "Remove",
        "Url": "http://placekitten.com/g/300/300"
    },
    {
        "ProductId": "50175acc-dfbf-43ac-86aa-aee37f804f5c",
        "Status": "Using",
        "Url": "http://placekitten.com/g/300/300"
    },
    {
        "ProductId": "3eac1cc3-3166-4d1d-a8f0-59d32f0468be",
        "Status": "Using",
        "Url": "http://placekitten.com/g/300/300"
    },
    {
        "ProductId": "edbc6b1c-5e84-4127-bce3-67fb47bc11e4",
        "Status": "Using",
        "Url": "http://placekitten.com/g/300/300"
    },
    {
        "ProductId": "907deaf0-cba5-491e-ab42-a20bbaaa040b",
        "Status": "Using",
        "Url": "http://placekitten.com/g/300/300"
    },
    {
        "ProductId": "02d9d1f8-2761-429d-b47f-1d45f62b1802",
        "Status": "Using",
        "Url": "http://placekitten.com/g/300/300"
    },
    {
        "ProductId": "a2bf8a79-705e-47d4-a2bd-44049337d60b",
        "Status": "Using",
        "Url": "http://placekitten.com/g/300/300"
    },
    {
        "ProductId": "e340e14b-d498-4115-8698-6f7b7a5b8a5f",
        "Status": "Using",
        "Url": "http://placekitten.com/g/300/300"
    },
    {
        "ProductId": "05420a89-ea89-40ca-bc5c-cd12f1afaf09",
        "Status": "Using",
        "Url": "http://placekitten.com/g/300/300"
    },
    {
        "ProductId": "ce72684b-569f-4427-a539-f71f4c134372",
        "Status": "Using",
        "Url": "http://placekitten.com/g/300/300"
    },
    {
        "ProductId": "2a6557e9-7727-4854-9ac6-44756849bd41",
        "Status": "Using",
        "Url": "http://placekitten.com/g/300/300"
    },
    {
        "ProductId": "a8238610-ba6a-44eb-a229-c1f90647bcf3",
        "Status": "Using",
        "Url": "http://placekitten.com/g/300/300"
    },
    {
        "ProductId": "f0cb29ba-76d0-4737-8565-5de26e4c24e4",
        "Status": "Using",
        "Url": "http://placekitten.com/g/300/300"
    },
    {
        "ProductId": "22c4b828-0c4d-42ae-9c9e-d339c1fa951d",
        "Status": "Using",
        "Url": "http://placekitten.com/g/300/300"
    },
    {
        "ProductId": "f54924cc-8c8a-4afc-869a-d67c89815e8c",
        "Status": "Using",
        "Url": "http://placekitten.com/g/300/300"
    },
    {
        "ProductId": "b285cf2b-55ea-4d7a-acf3-3f32ae27f195",
        "Status": "Using",
        "Url": "http://placekitten.com/g/300/300"
    },
    {
        "ProductId": "118cda2b-cb82-4749-bd07-3d4bee175bb6",
        "Status": "Using",
        "Url": "http://placekitten.com/g/300/300"
    },
    {
        "ProductId": "2d8fbdae-3835-4d03-8d20-924c1f6f6910",
        "Status": "Using",
        "Url": "http://placekitten.com/g/300/300"
    },
    {
        "ProductId": "9de69a44-fee2-4c0a-b3c9-4d05e14ded8f",
        "Status": "Using",
        "Url": "http://placekitten.com/g/300/300"
    },
    {
        "ProductId": "bc169dab-5c24-4fd5-af97-5e4a27121f69",
        "Status": "Using",
        "Url": "http://placekitten.com/g/300/300"
    },
    {
        "ProductId": "326ad98f-948c-4081-95c3-298dfe46a705",
        "Status": "Using",
        "Url": "http://placekitten.com/g/300/300"
    },
    {
        "ProductId": "54d5e86b-f4fc-43a8-8fbf-a3d3733f6d85",
        "Status": "Using",
        "Url": "http://placekitten.com/g/300/300"
    },
    {
        "ProductId": "3eac1cc3-3166-4d1d-a8f0-59d32f0468be",
        "Status": "Using",
        "Url": "http://placekitten.com/g/300/300"
    },
    {
        "ProductId": "edbc6b1c-5e84-4127-bce3-67fb47bc11e4",
        "Status": "Using",
        "Url": "http://placekitten.com/g/300/300"
    },
    {
        "ProductId": "907deaf0-cba5-491e-ab42-a20bbaaa040b",
        "Status": "Using",
        "Url": "http://placekitten.com/g/300/300"
    },
    {
        "ProductId": "02d9d1f8-2761-429d-b47f-1d45f62b1802",
        "Status": "Using",
        "Url": "http://placekitten.com/g/300/300"
    },
    {
        "ProductId": "a2bf8a79-705e-47d4-a2bd-44049337d60b",
        "Status": "Using",
        "Url": "http://placekitten.com/g/300/300"
    },
    {
        "ProductId": "e340e14b-d498-4115-8698-6f7b7a5b8a5f",
        "Status": "Using",
        "Url": "http://placekitten.com/g/300/300"
    },
    {
        "ProductId": "05420a89-ea89-40ca-bc5c-cd12f1afaf09",
        "Status": "Using",
        "Url": "http://placekitten.com/g/300/300"
    },
    {
        "ProductId": "ce72684b-569f-4427-a539-f71f4c134372",
        "Status": "Using",
        "Url": "http://placekitten.com/g/300/300"
    },
    {
        "ProductId": "2a6557e9-7727-4854-9ac6-44756849bd41",
        "Status": "Using",
        "Url": "http://placekitten.com/g/300/300"
    },
    {
        "ProductId": "a8238610-ba6a-44eb-a229-c1f90647bcf3",
        "Status": "Using",
        "Url": "http://placekitten.com/g/300/300"
    },
    {
        "ProductId": "f0cb29ba-76d0-4737-8565-5de26e4c24e4",
        "Status": "Using",
        "Url": "http://placekitten.com/g/300/300"
    },
    {
        "ProductId": "22c4b828-0c4d-42ae-9c9e-d339c1fa951d",
        "Status": "Using",
        "Url": "http://placekitten.com/g/300/300"
    },
    {
        "ProductId": "02d9d1f8-2761-429d-b47f-1d45f62b1802",
        "Status": "Using",
        "Url": "http://placekitten.com/g/300/300"
    },
    {
        "ProductId": "a2bf8a79-705e-47d4-a2bd-44049337d60b",
        "Status": "Using",
        "Url": "http://placekitten.com/g/300/300"
    },
    {
        "ProductId": "e340e14b-d498-4115-8698-6f7b7a5b8a5f",
        "Status": "Using",
        "Url": "http://placekitten.com/g/300/300"
    },
    {
        "ProductId": "05420a89-ea89-40ca-bc5c-cd12f1afaf09",
        "Status": "Using",
        "Url": "http://placekitten.com/g/300/300"
    },
    {
        "ProductId": "ce72684b-569f-4427-a539-f71f4c134372",
        "Status": "Using",
        "Url": "http://placekitten.com/g/300/300"
    },
    {
        "ProductId": "2a6557e9-7727-4854-9ac6-44756849bd41",
        "Status": "Using",
        "Url": "http://placekitten.com/g/300/300"
    },
    {
        "ProductId": "a8238610-ba6a-44eb-a229-c1f90647bcf3",
        "Status": "Using",
        "Url": "http://placekitten.com/g/300/300"
    },
    {
        "ProductId": "f0cb29ba-76d0-4737-8565-5de26e4c24e4",
        "Status": "Using",
        "Url": "http://placekitten.com/g/300/300"
    },
    {
        "ProductId": "22c4b828-0c4d-42ae-9c9e-d339c1fa951d",
        "Status": "Using",
        "Url": "http://placekitten.com/g/300/300"
    },
    {
        "ProductId": "f54924cc-8c8a-4afc-869a-d67c89815e8c",
        "Status": "Using",
        "Url": "http://placekitten.com/g/300/300"
    },
    {
        "ProductId": "b285cf2b-55ea-4d7a-acf3-3f32ae27f195",
        "Status": "Using",
        "Url": "http://placekitten.com/g/300/300"
    },
    {
        "ProductId": "2513250e-261d-4efa-b874-83cd1267c8ce",
        "Status": "Using",
        "Url": "http://placekitten.com/g/300/300"
    },
    {
        "ProductId": "7854cc1b-64ab-4062-aa0f-ba02aeb36ce6",
        "Status": "Using",
        "Url": "http://placekitten.com/g/300/300"
    },
    {
        "ProductId": "945ce915-201f-4605-b4cd-8db15ca5836b",
        "Status": "Using",
        "Url": "http://placekitten.com/g/300/300"
    },
    {
        "ProductId": "b285cf2b-55ea-4d7a-acf3-3f32ae27f195",
        "Status": "Using",
        "Url": "http://placekitten.com/g/300/300"
    },
    {
        "ProductId": "2513250e-261d-4efa-b874-83cd1267c8ce",
        "Status": "Using",
        "Url": "http://placekitten.com/g/300/300"
    },
    {
        "ProductId": "7854cc1b-64ab-4062-aa0f-ba02aeb36ce6",
        "Status": "Using",
        "Url": "http://placekitten.com/g/300/300"
    },
    {
        "ProductId": "945ce915-201f-4605-b4cd-8db15ca5836b",
        "Status": "Using",
        "Url": "http://placekitten.com/g/300/300"
    },
    {
        "ProductId": "4226947b-a632-45b1-9e3d-28b708fa91a9",
        "Status": "Using",
        "Url": "http://placekitten.com/g/300/300"
    },
    {
        "ProductId": "57f7fce4-1f00-4da9-bd57-2e1c30b1260a",
        "Status": "Using",
        "Url": "http://placekitten.com/g/300/300"
    },
    {
        "ProductId": "6d540f22-1587-4b73-bfd0-a467ae00ac22",
        "Status": "Using",
        "Url": "http://placekitten.com/g/300/300"
    },
    {
        "ProductId": "438838e4-ef46-4f60-af23-b8060c52ce78",
        "Status": "Using",
        "Url": "http://placekitten.com/g/300/300"
    },
    {
        "ProductId": "67a82b71-b359-48d2-84aa-fe4a6cd9be80",
        "Status": "Using",
        "Url": "http://placekitten.com/g/300/300"
    },
    {
        "ProductId": "d36210e7-e4c2-4826-b288-5a8f67ca5793",
        "Status": "Remove",
        "Url": "http://placekitten.com/g/300/300"
    },
    {
        "ProductId": "88dfcf99-43e4-4823-b88b-0cff516a5c38",
        "Status": "Using",
        "Url": "http://placekitten.com/g/300/300"
    },
    {
        "ProductId": "4b898315-cb1a-42b1-8a16-71f7e7a422d7",
        "Status": "Using",
        "Url": "http://placekitten.com/g/300/300"
    },
    {
        "ProductId": "c3773ce0-19aa-4e5e-8bd1-b579ff85c426",
        "Status": "Using",
        "Url": "http://placekitten.com/g/300/300"
    },
    {
        "ProductId": "299e65a7-5827-49b1-b08d-df237a7b01a7",
        "Status": "Using",
        "Url": "http://placekitten.com/g/300/300"
    },
    {
        "ProductId": "6b62b0f7-45a8-4032-8aeb-402af3ae8406",
        "Status": "Using",
        "Url": "http://placekitten.com/g/300/300"
    },
    {
        "ProductId": "6050fe69-74d3-4f50-9fc4-a78c4fc72609",
        "Status": "Using",
        "Url": "http://placekitten.com/g/300/300"
    },
    {
        "ProductId": "b065f698-e3b6-42d0-8534-75f6d27618e7",
        "Status": "Using",
        "Url": "http://placekitten.com/g/300/300"
    },
    {
        "ProductId": "bce11432-c2a8-4ad2-a49c-2a44bfe6a16d",
        "Status": "Using",
        "Url": "http://placekitten.com/g/300/300"
    },
    {
        "ProductId": "05420a89-ea89-40ca-bc5c-cd12f1afaf09",
        "Status": "Using",
        "Url": "http://placekitten.com/g/300/300"
    }
]